[
  {
    "nameId": "",
    "title": "Write the scientific term",
    "playerName": "",
    "dataContent": 0,
    "subject": "science-4 eng ",
    "colorTemplate": "#79D2E4",
    "counterFinished": 0,
    "inputCounter": 0,
    "counterCorrect": 0,
    "LODegree": null,
    "UserDegree": null,
    "type": "",
    "BloomTargets": [""],
    "randomNumber": null,
    "loTargets": null,
    "numberOfquestion": null,
    "items": [
      {
        "id": 1,
        "type": 1,
        "contents": [
          {
            "paragraphes1": [
              "The system responsible for obtaining the nutrients that support the rest of the body organs is the digestive system."
            ],
            "inputtype": [
              {
                "length": 0,
                "numperofinput": 1,
                "comma": "",
                "valid": ["Digestive system", "The digestive system"],
                "show": ["The digestive system"]
              }
            ],
            "inputtype2": [
              {
                "length": 0,
                "numperofinput": 0,
                "comma": "",
                "valid": [""],
                "show": [""]
              }
            ]
          }
        ],
        "showAnswer": [
          {
            "answer": [""],
            "correct": true
          }
        ],
        "answerUser": [
          {
            "answer": [""],
            "correct": false,
            "help": false,
            "done": false
          }
        ]
      },
      {
        "id": 1,
        "type": 1,
        "contents": [
          {
            "paragraphes1": [
              "The system responsible for pumping blood to muscles responsible for motion."
            ],
            "inputtype": [
              {
                "length": 0,
                "numperofinput": 1,
                "comma": "",
                "valid": ["circulatory system"],
                "show": ["Circulatory system"]
              }
            ],
            "inputtype2": [
              {
                "length": 0,
                "numperofinput": 0,
                "comma": "",
                "valid": [""],
                "show": [""]
              }
            ]
          }
        ],
        "showAnswer": [
          {
            "answer": [""],
            "correct": true
          }
        ],
        "answerUser": [
          {
            "answer": [""],
            "correct": false,
            "help": false,
            "done": false
          }
        ]
      }
    ]
  }
]
