[
  {
    "nameId": "",
    "title": "",
    "subject": "math-3 eng",
    "colorTemplate": "#8388C6",
    "counterFinished": 0,
    "inputCounter": 0,
    "hand": true,
    "pop": "",

    "counterCorrect": 0,
    "LODegree": null,
    "UserDegree": null,
    "type": "",
    "BloomTargets": [""],
    "randomNumber": null,
    "loTargets": null,
    "numberOfquestion": null,

    "inputSlide": [
      {
        "active": true,
        "paragraph1": [],
        "quran": [],
        "paragraph2": [],
        "title": "Complete the following",
        "qtitle": "Look carefully at the shaded part, then complete by writing the equivalent fraction, as shown in the example:",
        "full": true,
        "break": true,
        "left": false,
        "image": true,
        "index": true,
        "items": [
          {
            "id": 1,
            "example": true,
            "type": 2,
            "fractionOne": true,
            "fractionTwo": true,
            "fractionThree": false,
            "index": "",
            "contents": [
              {
                "paragraphes1": [""],
                "up1": "<span>3</span>",
                "down1": "<span>9</span>",
                "up": "2",
                "down": "6",
                "up2": "",
                "down2": "",
                "img": "../images/04_02/118/1.png",
                "inputtype": [
                  {
                    "length": 0,
                    "numperofinput": 0,
                    "comma": "",
                    "valid": [""],
                    "show": [""]
                  }
                ],
                "inputtype2": [
                  {
                    "length": 0,
                    "numperofinput": 0,
                    "comma": "",
                    "valid": ["3"],
                    "show": ["3"]
                  },
                  {
                    "length": 0,
                    "numperofinput": 0,
                    "comma": "",
                    "valid": ["6"],
                    "show": ["6"]
                  },
                  {
                    "length": 0,
                    "numperofinput": 0,
                    "comma": "",
                    "valid": ["1"],
                    "show": ["1"]
                  },
                  {
                    "length": 0,
                    "numperofinput": 0,
                    "comma": "",
                    "valid": ["6"],
                    "show": ["6"]
                  },
                  {
                    "length": 0,
                    "numperofinput": 0,
                    "comma": "",
                    "valid": ["4"],
                    "show": ["4"]
                  },
                  {
                    "length": 0,
                    "numperofinput": 0,
                    "comma": "",
                    "valid": ["6"],
                    "show": ["6"]
                  }
                ],
                "paragraphes2": ["="],
                "paragraphes3": [""]
              }
            ],
            "answerUser": [
              {
                "answer": [""],
                "correct": false,
                "help": false,
                "done": false
              },
              {
                "answer": [""],
                "correct": false,
                "help": false,
                "done": false
              },
              {
                "answer": [""],
                "correct": false,
                "help": false,
                "done": false
              },
              {
                "answer": [""],
                "correct": false,
                "help": false,
                "done": false
              },
              {
                "answer": [""],
                "correct": false,
                "help": false,
                "done": false
              },
              {
                "answer": [""],
                "correct": false,
                "help": false,
                "done": false
              }
            ]
          },
          {
            "id": 1,
            "type": 2,
            "index": 1,
            "fractionOne": true,
            "fractionTwo": true,
            "fractionThree": false,

            "contents": [
              {
                "up": "",
                "down": "",
                "up1": "4",
                "down1": "8",
                "up2": "",
                "down2": "",
                "paragraphes1": [""],
                "img": "../images/04_02/118/2.png",
                "inputtype": [
                  {
                    "length": 0,
                    "numperofinput": 0,
                    "comma": "",
                    "valid": [""],
                    "show": [""]
                  }
                ],
                "inputtype2": [
                  {
                    "length": 0,
                    "numperofinput": 1,
                    "comma": "",
                    "valid": ["1"],
                    "show": ["1"]
                  },
                  {
                    "length": 0,
                    "numperofinput": 1,
                    "comma": "",
                    "valid": ["2"],
                    "show": ["2"]
                  },
                  {
                    "length": 0,
                    "numperofinput": 0,
                    "comma": "",
                    "valid": ["0"],
                    "show": ["0"]
                  },
                  {
                    "length": 0,
                    "numperofinput": 0,
                    "comma": "",
                    "valid": ["2"],
                    "show": ["2"]
                  },
                  {
                    "length": 0,
                    "numperofinput": 0,
                    "comma": "",
                    "valid": ["0"],
                    "show": ["0"]
                  },
                  {
                    "length": 0,
                    "numperofinput": 0,
                    "comma": "",
                    "valid": ["8"],
                    "show": ["8"]
                  }
                ],
                "paragraphes2": ["="],
                "paragraphes3": [""]
              }
            ],
            "answerUser": [
              {
                "answer": [""],
                "correct": false,
                "help": false,
                "done": false
              },
              {
                "answer": [""],
                "correct": false,
                "help": false,
                "done": false
              },
              {
                "answer": [""],
                "correct": false,
                "help": false,
                "done": false
              },
              {
                "answer": [""],
                "correct": false,
                "help": false,
                "done": false
              },
              {
                "answer": [""],
                "correct": false,
                "help": false,
                "done": false
              },
              {
                "answer": [""],
                "correct": false,
                "help": false,
                "done": false
              }
            ]
          },
          {
            "id": 1,
            "type": 2,
            "index": 2,
            "fractionOne": true,
            "fractionTwo": true,
            "fractionThree": false,

            "contents": [
              {
                "up1": "1",
                "down1": "2",
                "up": "",
                "down": "",
                "up2": "",
                "down2": "",
                "paragraphes1": [""],
                "img": "../images/04_02/118/3.png",
                "inputtype": [
                  {
                    "length": 0,
                    "numperofinput": 0,
                    "comma": "",
                    "valid": [""],
                    "show": [""]
                  }
                ],
                "inputtype2": [
                  {
                    "length": 0,
                    "numperofinput": 1,
                    "comma": "",
                    "valid": ["7"],
                    "show": ["7"]
                  },
                  {
                    "length": 0,
                    "numperofinput": 1,
                    "comma": "",
                    "valid": ["14"],
                    "show": ["14"]
                  },
                  {
                    "length": 0,
                    "numperofinput": 0,
                    "comma": "",
                    "valid": ["7"],
                    "show": ["7"]
                  },
                  {
                    "length": 0,
                    "numperofinput": 0,
                    "comma": "",
                    "valid": ["14"],
                    "show": ["14"]
                  },
                  {
                    "length": 0,
                    "numperofinput": 0,
                    "comma": "",
                    "valid": ["0"],
                    "show": ["0"]
                  },
                  {
                    "length": 0,
                    "numperofinput": 0,
                    "comma": "",
                    "valid": ["8"],
                    "show": ["8"]
                  }
                ],
                "paragraphes2": ["="],
                "paragraphes3": [""]
              }
            ],
            "answerUser": [
              {
                "answer": [""],
                "correct": false,
                "help": false,
                "done": false
              },
              {
                "answer": [""],
                "correct": false,
                "help": false,
                "done": false
              },
              {
                "answer": [""],
                "correct": false,
                "help": false,
                "done": false
              },
              {
                "answer": [""],
                "correct": false,
                "help": false,
                "done": false
              },
              {
                "answer": [""],
                "correct": false,
                "help": false,
                "done": false
              },
              {
                "answer": [""],
                "correct": false,
                "help": false,
                "done": false
              }
            ]
          },
          {
            "id": 1,
            "type": 2,
            "index": 3,
            "fractionOne": true,
            "fractionTwo": true,
            "fractionThree": false,

            "contents": [
              {
                "up1": "2",
                "down1": "3",
                "up": "",
                "down": "",
                "up2": "",
                "down2": "",
                "paragraphes1": [""],
                "img": "../images/04_02/118/4.png",
                "inputtype": [
                  {
                    "length": 0,
                    "numperofinput": 0,
                    "comma": "",
                    "valid": [""],
                    "show": [""]
                  }
                ],
                "inputtype2": [
                  {
                    "length": 0,
                    "numperofinput": 1,
                    "comma": "",
                    "valid": ["6"],
                    "show": ["6"]
                  },
                  {
                    "length": 0,
                    "numperofinput": 1,
                    "comma": "",
                    "valid": ["9"],
                    "show": ["9"]
                  },
                  {
                    "length": 0,
                    "numperofinput": 0,
                    "comma": "",
                    "valid": ["6"],
                    "show": ["6"]
                  },
                  {
                    "length": 0,
                    "numperofinput": 0,
                    "comma": "",
                    "valid": ["9"],
                    "show": ["9"]
                  },
                  {
                    "length": 0,
                    "numperofinput": 0,
                    "comma": "",
                    "valid": ["0"],
                    "show": ["0"]
                  },
                  {
                    "length": 0,
                    "numperofinput": 0,
                    "comma": "",
                    "valid": ["8"],
                    "show": ["8"]
                  }
                ],
                "paragraphes2": ["="],
                "paragraphes3": [""]
              }
            ],
            "answerUser": [
              {
                "answer": [""],
                "correct": false,
                "help": false,
                "done": false
              },
              {
                "answer": [""],
                "correct": false,
                "help": false,
                "done": false
              },
              {
                "answer": [""],
                "correct": false,
                "help": false,
                "done": false
              },
              {
                "answer": [""],
                "correct": false,
                "help": false,
                "done": false
              },
              {
                "answer": [""],
                "correct": false,
                "help": false,
                "done": false
              },
              {
                "answer": [""],
                "correct": false,
                "help": false,
                "done": false
              }
            ]
          },
          {
            "id": 1,
            "type": 2,
            "index": 4,
            "fractionOne": true,
            "fractionTwo": true,
            "fractionThree": false,

            "contents": [
              {
                "up1": "4",
                "down1": "12",
                "up": "",
                "down": "",
                "up2": "",
                "down2": "",
                "paragraphes1": [""],
                "img": "../images/04_02/118/5.png",
                "inputtype": [
                  {
                    "length": 0,
                    "numperofinput": 0,
                    "comma": "",
                    "valid": [""],
                    "show": [""]
                  }
                ],
                "inputtype2": [
                  {
                    "length": 0,
                    "numperofinput": 1,
                    "comma": "",
                    "valid": ["2"],
                    "show": ["2"]
                  },
                  {
                    "length": 0,
                    "numperofinput": 1,
                    "comma": "",
                    "valid": ["6"],
                    "show": ["6"]
                  },
                  {
                    "length": 0,
                    "numperofinput": 0,
                    "comma": "",
                    "valid": ["2"],
                    "show": ["2"]
                  },
                  {
                    "length": 0,
                    "numperofinput": 0,
                    "comma": "",
                    "valid": ["6"],
                    "show": ["6"]
                  },
                  {
                    "length": 0,
                    "numperofinput": 0,
                    "comma": "",
                    "valid": ["0"],
                    "show": ["0"]
                  },
                  {
                    "length": 0,
                    "numperofinput": 0,
                    "comma": "",
                    "valid": ["8"],
                    "show": ["8"]
                  }
                ],
                "paragraphes2": ["="],
                "paragraphes3": [""]
              }
            ],
            "answerUser": [
              {
                "answer": [""],
                "correct": false,
                "help": false,
                "done": false
              },
              {
                "answer": [""],
                "correct": false,
                "help": false,
                "done": false
              },
              {
                "answer": [""],
                "correct": false,
                "help": false,
                "done": false
              },
              {
                "answer": [""],
                "correct": false,
                "help": false,
                "done": false
              },
              {
                "answer": [""],
                "correct": false,
                "help": false,
                "done": false
              },
              {
                "answer": [""],
                "correct": false,
                "help": false,
                "done": false
              }
            ]
          },
          {
            "id": 1,
            "type": 2,
            "index": 5,
            "fractionOne": true,
            "fractionTwo": true,
            "fractionThree": false,

            "contents": [
              {
                "up1": "3",
                "down1": "4",
                "up": "",
                "down": "",
                "up2": "",
                "down2": "",
                "paragraphes1": [""],
                "img": "../images/04_02/118/6.png",
                "inputtype": [
                  {
                    "length": 0,
                    "numperofinput": 0,
                    "comma": "",
                    "valid": [""],
                    "show": [""]
                  }
                ],
                "inputtype2": [
                  {
                    "length": 0,
                    "numperofinput": 1,
                    "comma": "",
                    "valid": ["6"],
                    "show": ["6"]
                  },
                  {
                    "length": 0,
                    "numperofinput": 1,
                    "comma": "",
                    "valid": ["8"],
                    "show": ["8"]
                  },
                  {
                    "length": 0,
                    "numperofinput": 0,
                    "comma": "",
                    "valid": ["6"],
                    "show": ["6"]
                  },
                  {
                    "length": 0,
                    "numperofinput": 0,
                    "comma": "",
                    "valid": ["8"],
                    "show": ["8"]
                  },
                  {
                    "length": 0,
                    "numperofinput": 0,
                    "comma": "",
                    "valid": ["0"],
                    "show": ["0"]
                  },
                  {
                    "length": 0,
                    "numperofinput": 0,
                    "comma": "",
                    "valid": ["8"],
                    "show": ["8"]
                  }
                ],
                "paragraphes2": ["="],
                "paragraphes3": [""]
              }
            ],
            "answerUser": [
              {
                "answer": [""],
                "correct": false,
                "help": false,
                "done": false
              },
              {
                "answer": [""],
                "correct": false,
                "help": false,
                "done": false
              },
              {
                "answer": [""],
                "correct": false,
                "help": false,
                "done": false
              },
              {
                "answer": [""],
                "correct": false,
                "help": false,
                "done": false
              },
              {
                "answer": [""],
                "correct": false,
                "help": false,
                "done": false
              },
              {
                "answer": [""],
                "correct": false,
                "help": false,
                "done": false
              }
            ]
          },
          {
            "id": 1,
            "type": 2,
            "index": 6,
            "fractionOne": true,
            "fractionTwo": true,
            "fractionThree": false,

            "contents": [
              {
                "up1": "1",
                "down1": "5",
                "up": "",
                "down": "",
                "up2": "",
                "down2": "",
                "paragraphes1": [""],
                "img": "../images/04_02/118/7.png",
                "inputtype": [
                  {
                    "length": 0,
                    "numperofinput": 0,
                    "comma": "",
                    "valid": [""],
                    "show": [""]
                  }
                ],
                "inputtype2": [
                  {
                    "length": 0,
                    "numperofinput": 1,
                    "comma": "",
                    "valid": ["2"],
                    "show": ["2"]
                  },
                  {
                    "length": 0,
                    "numperofinput": 1,
                    "comma": "",
                    "valid": ["10"],
                    "show": ["10"]
                  },
                  {
                    "length": 0,
                    "numperofinput": 0,
                    "comma": "",
                    "valid": ["2"],
                    "show": ["2"]
                  },
                  {
                    "length": 0,
                    "numperofinput": 0,
                    "comma": "",
                    "valid": ["20"],
                    "show": ["20"]
                  },
                  {
                    "length": 0,
                    "numperofinput": 0,
                    "comma": "",
                    "valid": ["0"],
                    "show": ["0"]
                  },
                  {
                    "length": 0,
                    "numperofinput": 0,
                    "comma": "",
                    "valid": ["8"],
                    "show": ["8"]
                  }
                ],
                "paragraphes2": ["="],
                "paragraphes3": [""]
              }
            ],
            "answerUser": [
              {
                "answer": [""],
                "correct": false,
                "help": false,
                "done": false
              },
              {
                "answer": [""],
                "correct": false,
                "help": false,
                "done": false
              },
              {
                "answer": [""],
                "correct": false,
                "help": false,
                "done": false
              },
              {
                "answer": [""],
                "correct": false,
                "help": false,
                "done": false
              },
              {
                "answer": [""],
                "correct": false,
                "help": false,
                "done": false
              },
              {
                "answer": [""],
                "correct": false,
                "help": false,
                "done": false
              }
            ]
          },
          {
            "id": 1,
            "type": 2,
            "index": 7,
            "fractionOne": true,
            "fractionTwo": true,
            "fractionThree": false,

            "contents": [
              {
                "up1": "4",
                "down1": "5",
                "up": "",
                "down": "",
                "up2": "",
                "down2": "",
                "paragraphes1": [""],
                "img": "../images/04_02/118/8.png",
                "inputtype": [
                  {
                    "length": 0,
                    "numperofinput": 0,
                    "comma": "",
                    "valid": [""],
                    "show": [""]
                  }
                ],
                "inputtype2": [
                  {
                    "length": 0,
                    "numperofinput": 1,
                    "comma": "",
                    "valid": ["8"],
                    "show": ["8"]
                  },
                  {
                    "length": 0,
                    "numperofinput": 1,
                    "comma": "",
                    "valid": ["10"],
                    "show": ["10"]
                  },
                  {
                    "length": 0,
                    "numperofinput": 0,
                    "comma": "",
                    "valid": ["8"],
                    "show": ["8"]
                  },
                  {
                    "length": 0,
                    "numperofinput": 0,
                    "comma": "",
                    "valid": ["10"],
                    "show": ["10"]
                  },
                  {
                    "length": 0,
                    "numperofinput": 0,
                    "comma": "",
                    "valid": ["0"],
                    "show": ["0"]
                  },
                  {
                    "length": 0,
                    "numperofinput": 0,
                    "comma": "",
                    "valid": ["8"],
                    "show": ["8"]
                  }
                ],
                "paragraphes2": ["="],
                "paragraphes3": [""]
              }
            ],
            "answerUser": [
              {
                "answer": [""],
                "correct": false,
                "help": false,
                "done": false
              },
              {
                "answer": [""],
                "correct": false,
                "help": false,
                "done": false
              },
              {
                "answer": [""],
                "correct": false,
                "help": false,
                "done": false
              },
              {
                "answer": [""],
                "correct": false,
                "help": false,
                "done": false
              },
              {
                "answer": [""],
                "correct": false,
                "help": false,
                "done": false
              },
              {
                "answer": [""],
                "correct": false,
                "help": false,
                "done": false
              }
            ]
          }
        ],
        "popupQuestion": [
          {
            "id": 0,
            "type": 3,
            "index": "",
            "paragraph": "",
            "popup": [""],
            "isActive": null
          }
        ]
      }
    ],
    "popup": false,
    "popuptext": ""
  }
]
